aprsd_avwx_plugin/__init__.py
aprsd_avwx_plugin/aprsd_avwx_plugin.py
aprsd_avwx_plugin/conf/__init__.py
aprsd_avwx_plugin/conf/main.py
aprsd_avwx_plugin/conf/opts.py
aprsd_avwx_plugin-1.0.0.dist-info/licenses/LICENSE
aprsd_avwx_plugin-1.0.0.dist-info/METADATA
aprsd_avwx_plugin-1.0.0.dist-info/WHEEL
aprsd_avwx_plugin-1.0.0.dist-info/entry_points.txt
aprsd_avwx_plugin-1.0.0.dist-info/top_level.txt
aprsd_avwx_plugin-1.0.0.dist-info/RECORD
